figcli/__init__.py
figcli/__main__.py
figcli/commands/__init__.py
figcli/commands/command_context.py
figcli/commands/command_factory.py
figcli/commands/config_context.py
figcli/commands/config_factory.py
figcli/commands/factory.py
figcli/commands/figgy_context.py
figcli/commands/help_context.py
figcli/commands/help_factory.py
figcli/commands/iam_context.py
figcli/commands/iam_factory.py
figcli/commands/maintenance_context.py
figcli/commands/maintenance_factory.py
figcli/commands/ots_context.py
figcli/commands/ots_factory.py
figcli/commands/ui_factory.py
figcli/commands/config/__init__.py
figcli/commands/config/audit.py
figcli/commands/config/browse.py
figcli/commands/config/build_cache.py
figcli/commands/config/delete.py
figcli/commands/config/dump.py
figcli/commands/config/edit.py
figcli/commands/config/generate.py
figcli/commands/config/get.py
figcli/commands/config/list.py
figcli/commands/config/promote.py
figcli/commands/config/prune.py
figcli/commands/config/put.py
figcli/commands/config/restore.py
figcli/commands/config/share.py
figcli/commands/config/sync.py
figcli/commands/config/ui.py
figcli/commands/config/validate.py
figcli/commands/help/__init__.py
figcli/commands/help/configure.py
figcli/commands/help/login.py
figcli/commands/help/upgrade.py
figcli/commands/help/version.py
figcli/commands/iam/__init__.py
figcli/commands/iam/export.py
figcli/commands/iam/restore.py
figcli/commands/maintenance/__init__.py
figcli/commands/one_time_secret/__init__.py
figcli/commands/one_time_secret/get.py
figcli/commands/one_time_secret/put.py
figcli/commands/types/__init__.py
figcli/commands/types/command.py
figcli/commands/types/config.py
figcli/commands/types/help.py
figcli/commands/types/iam.py
figcli/commands/types/maintenance.py
figcli/commands/types/one_time_secret.py
figcli/config/__init__.py
figcli/config/aws.py
figcli/config/commands.py
figcli/config/communication.py
figcli/config/constants.py
figcli/config/figgy.py
figcli/config/sso.py
figcli/config/tuning.py
figgy_cli-1.2.10.dist-info/LICENSE
figgy_cli-1.2.10.dist-info/METADATA
figgy_cli-1.2.10.dist-info/WHEEL
figgy_cli-1.2.10.dist-info/entry_points.txt
figgy_cli-1.2.10.dist-info/top_level.txt
figgy_cli-1.2.10.dist-info/RECORD
