Metadata-Version: 2.1
Name: figgy-cli
Version: 1.2.10
Summary: Tired of managing hundreds or thousands of configurations as your microservice footprint scales? Tired of config files, environment variables, poorly managed secrets, and  constantly crashing containers due to configuration mismanagement? There’s a better way. Figgy!
Home-page: https://figgy.dev
Author: Jordan Mance
Author-email: jordan@figgy.dev
License: UNKNOWN
Platform: UNKNOWN
Classifier: Programming Language :: Python :: 3
Classifier: Environment :: Console
Classifier: Intended Audience :: Developers
Classifier: License :: OSI Approved :: Apache Software License
Classifier: Operating System :: OS Independent
Classifier: Natural Language :: English
Classifier: Programming Language :: Python :: 3.5
Classifier: Programming Language :: Python :: 3.6
Classifier: Programming Language :: Python :: 3.7
Classifier: Programming Language :: Python :: Implementation
Classifier: Topic :: Terminals
Classifier: Topic :: Utilities
Requires-Python: >=3.7
License-File: LICENSE
Requires-Dist: boto3 (>=1.13.19)
Requires-Dist: prompt-toolkit (==2.0.7)
Requires-Dist: sty (>=1.0.0b12)
Requires-Dist: click (>=7.1.2)
Requires-Dist: tqdm (>=4.46.0)
Requires-Dist: npyscreen (>=4.10.5)
Requires-Dist: beautifulsoup4 (>=4.9.1)
Requires-Dist: keyring (>=21.2.1)
Requires-Dist: keyrings.alt (>=3.4.0)
Requires-Dist: tabulate (>=0.8.7)
Requires-Dist: jsonpickle (>=1.4.1)
Requires-Dist: urllib3 (>=1.25.7)
Requires-Dist: pyotp (>=2.3.0)
Requires-Dist: pydantic (>=1.5.1)
Requires-Dist: python-u2flib-host (>=3.0.3)
Requires-Dist: pycryptodome (>=3.9.7)
Requires-Dist: filelock (>=3.0.12)
Requires-Dist: pygments (>=2.6.1)
